LICENSE
README.md
pyproject.toml
setup.cfg
setup.py
src/masonite_package_sync/__init__.py
src/masonite_package_sync/main.py
src/masonite_package_sync/utils.py
src/masonite_package_sync.egg-info/PKG-INFO
src/masonite_package_sync.egg-info/SOURCES.txt
src/masonite_package_sync.egg-info/dependency_links.txt
src/masonite_package_sync.egg-info/entry_points.txt
src/masonite_package_sync.egg-info/requires.txt
src/masonite_package_sync.egg-info/top_level.txt
src/masonite_package_sync/commands/PullCommand.py
src/masonite_package_sync/commands/__init__.py