Metadata-Version: 2.1
Name: masonite-package-sync
Version: 0.4.0
Summary: Masonite package synchronisation
Home-page: https://github.com/girardinsamuel/masonite-package-sync
Author: Samuel Girardin
Author-email: sam@masoniteproject.com
License: MIT
Keywords: Masonite,MasoniteFramework,Python,Packages
Platform: UNKNOWN
Classifier: Development Status :: 4 - Beta
Classifier: Intended Audience :: Developers
Classifier: Topic :: Software Development :: Build Tools
Classifier: Environment :: Web Environment
Classifier: License :: OSI Approved :: MIT License
Classifier: Operating System :: OS Independent
Classifier: Programming Language :: Python :: 3.6
Classifier: Programming Language :: Python :: 3.7
Classifier: Programming Language :: Python :: 3.8
Classifier: Programming Language :: Python :: 3.9
Classifier: Programming Language :: Python :: 3.10
Classifier: Topic :: Software Development :: Libraries :: Python Modules
Provides-Extra: test
